otcyto/__init__.py
otcyto/check_pykeops.py
otcyto/otd_pairwise.py
otcyto/geomloss/README.md
otcyto/geomloss/__init__.py
otcyto/geomloss/create_sphere.py
otcyto/io/__init__.py
otcyto/io/load_files_recursive.py
otcyto/plot/__init__.py
otcyto/plot/display_cloud.py
otcyto/plot/display_cloud_mapping.py
otcyto/plot/figure_clouds.py
otcyto/plot/figure_umap.py
otcyto-0.1.0.dist-info/licenses/LICENSE.txt
otcyto-0.1.0.dist-info/METADATA
otcyto-0.1.0.dist-info/WHEEL
otcyto-0.1.0.dist-info/top_level.txt
otcyto-0.1.0.dist-info/RECORD
