Metadata-Version: 2.4
Name: otcyto
Version: 0.1.0
Summary: Optimal transport for cytometry data
Home-page: https://github.com/pyscaffold/pyscaffold/
Author-email: gunthergl_r2 <gunthergl@gmx.net>
License: MIT
Requires-Python: >=3.10
License-File: LICENSE.txt
Requires-Dist: matplotlib
Requires-Dist: pykeops
Requires-Dist: torch
Requires-Dist: geomloss
Requires-Dist: pandas
Requires-Dist: pyarrow
Dynamic: license-file
